setup.py
pyidenticon/__init__.py
pyidenticon/blocks.py
pyidenticon.egg-info/PKG-INFO
pyidenticon.egg-info/SOURCES.txt
pyidenticon.egg-info/dependency_links.txt
pyidenticon.egg-info/requires.txt
pyidenticon.egg-info/top_level.txt