Metadata-Version: 1.0
Name: pyidenticon
Version: 0.0.1
Summary: A identicon python implementation.
Home-page: https://github.com/jeremaihloo/pyidenticon
Author: jeremaihloo
Author-email: jeremaihloo1024@gmail.com
License: UNKNOWN
Platform: UNKNOWN
